nion/swift/ActivityPanel.py
nion/swift/Application.py
nion/swift/ComputationPanel.py
nion/swift/ConsoleDialog.py
nion/swift/DataItemThumbnailWidget.py
nion/swift/DataPanel.py
nion/swift/DisplayCanvasItem.py
nion/swift/DisplayEditPopup.py
nion/swift/DisplayPanel.py
nion/swift/DocumentController.py
nion/swift/EntityBrowser.py
nion/swift/ExportDialog.py
nion/swift/Facade.py
nion/swift/FacadeQueued.py
nion/swift/FilterPanel.py
nion/swift/GeneratorDialog.py
nion/swift/HistogramPanel.py
nion/swift/ImageCanvasItem.py
nion/swift/InfoPanel.py
nion/swift/Inspector.py
nion/swift/LineGraphCanvasItem.py
nion/swift/LinePlotCanvasItem.py
nion/swift/MetadataPanel.py
nion/swift/MimeTypes.py
nion/swift/NotificationDialog.py
nion/swift/Panel.py
nion/swift/ProjectItemsDialog.py
nion/swift/ProjectPanel.py
nion/swift/RecorderPanel.py
nion/swift/ScriptsDialog.py
nion/swift/SessionPanel.py
nion/swift/Task.py
nion/swift/Test.py
nion/swift/Thumbnails.py
nion/swift/ToolbarPanel.py
nion/swift/Undo.py
nion/swift/Workspace.py
nion/swift/__init__.py
nion/swift/command.py
nion/swift/py.typed
nion/swift/model/Activity.py
nion/swift/model/ApplicationData.py
nion/swift/model/Cache.py
nion/swift/model/Changes.py
nion/swift/model/ColorMaps.py
nion/swift/model/Connection.py
nion/swift/model/Connector.py
nion/swift/model/DataGroup.py
nion/swift/model/DataItem.py
nion/swift/model/DataStructure.py
nion/swift/model/DisplayItem.py
nion/swift/model/DocumentModel.py
nion/swift/model/DynamicString.py
nion/swift/model/Feature.py
nion/swift/model/FileStorageSystem.py
nion/swift/model/Graphics.py
nion/swift/model/HDF5Handler.py
nion/swift/model/HardwareSource.py
nion/swift/model/ImportExportManager.py
nion/swift/model/Metadata.py
nion/swift/model/Migration.py
nion/swift/model/Model.py
nion/swift/model/NDataHandler.py
nion/swift/model/Notification.py
nion/swift/model/Observer.py
nion/swift/model/Persistence.py
nion/swift/model/PlugInManager.py
nion/swift/model/Processing.py
nion/swift/model/Profile.py
nionswift-16.16.2.dist-info/licenses/LICENSE
nionswift-16.16.2.dist-info/METADATA
nionswift-16.16.2.dist-info/WHEEL
nionswift-16.16.2.dist-info/entry_points.txt
nionswift-16.16.2.dist-info/top_level.txt
nionswift-16.16.2.dist-info/RECORD
