Metadata-Version: 2.4
Name: nionswift
Version: 16.16.2
Summary: Nion Swift: Scientific Image Processing.
Home-page: https://github.com/nion-software/nionswift
Author: Nion Software
Author-email: swift@nion.com
License: GPL-3.0-only
Classifier: Development Status :: 5 - Production/Stable
Classifier: License :: OSI Approved :: GNU General Public License v3 (GPLv3)
Classifier: Programming Language :: Python :: 3.11
Classifier: Programming Language :: Python :: 3.12
Classifier: Programming Language :: Python :: 3.13
Requires-Python: >=3.11
License-File: LICENSE
Requires-Dist: scipy
Requires-Dist: numpy<3.0,>=2.0
Requires-Dist: h5py
Requires-Dist: pytz
Requires-Dist: tzlocal
Requires-Dist: imageio>=2.19.0
Requires-Dist: pillow
Requires-Dist: niondata<16.0,>=15.9
Requires-Dist: nionui<11.0,>=10.2
Requires-Dist: nionswift-io<16.0,>=15.5
Requires-Dist: nionutils<5.0,>=4.14
Dynamic: license-file
